mainframe_paxo/.gitattributes
mainframe_paxo/__init__.py
mainframe_paxo/__main__.py
mainframe_paxo/config.py
mainframe_paxo/log.py
mainframe_paxo/p4.py
mainframe_paxo/package_data.dat
mainframe_paxo/paxo.ico
mainframe_paxo/paxo.py
mainframe_paxo/py.py
mainframe_paxo/registry.py
mainframe_paxo/simple.py
mainframe_paxo/tools.py
mainframe_paxo/ue.py
mainframe_paxo/uvs.py
mainframe_paxo/uvs_gui.py
mainframe_paxo/vstudio.py
mainframe_paxo/winget.py
mainframe_paxo/uebase/__init__.py
mainframe_paxo/uebase/config_cache.py
mainframe_paxo/uebase/desktop.py
mainframe_paxo/uebase/desktop_win.py
mainframe_paxo/uebase/paths.py
mainframe_paxo/uebase/platform.py
mainframe_paxo-0.1.30.dist-info/METADATA
mainframe_paxo-0.1.30.dist-info/WHEEL
mainframe_paxo-0.1.30.dist-info/entry_points.txt
mainframe_paxo-0.1.30.dist-info/licenses/LICENSE.txt
mainframe_paxo-0.1.30.dist-info/RECORD
